mdiss/__init__.py
mdiss/analyzer.py
mdiss/cli.py
mdiss/clients/__init__.py
mdiss/clients/gitlab_client.py
mdiss/github_client.py
mdiss/models.py
mdiss/notification/slack.py
mdiss/parser/README.md
mdiss/parser/__init__.py
mdiss/parser/base_parser.py
mdiss/parser/exceptions.py
mdiss/parser/handlers/__init__.py
mdiss/parser/handlers/code_block_parser.py
mdiss/parser/handlers/todo_format.py
mdiss/parser/main.py
mdiss/parser/models/__init__.py
mdiss/parser/utils/__init__.py
mdiss/parser.py
mdiss/parsers/__init__.py
mdiss/parsers/json_parser.py
mdiss/parsers/xml_parser.py
mdiss/parsers/yml_parser.py
mdiss-2.0.1.dist-info/LICENSE
mdiss-2.0.1.dist-info/METADATA
mdiss-2.0.1.dist-info/WHEEL
mdiss-2.0.1.dist-info/entry_points.txt
mdiss-2.0.1.dist-info/RECORD
