Metadata-Version: 2.3
Name: mdiss
Version: 2.0.1
Summary: Automatyczne generowanie ticketów GitHub na podstawie plików markdown z błędami poleceń
License: Apache-2.0
Keywords: github,issues,automation,markdown,ci,build
Author: Tom Sapletta
Author-email: info@softreck.dev
Maintainer: WRONAI Team
Requires-Python: >=3.9,<4.0
Classifier: Development Status :: 4 - Beta
Classifier: Intended Audience :: Developers
Classifier: License :: OSI Approved :: Apache Software License
Classifier: Operating System :: OS Independent
Classifier: Programming Language :: Python :: 3
Classifier: Programming Language :: Python :: 3.9
Classifier: Programming Language :: Python :: 3.10
Classifier: Programming Language :: Python :: 3.11
Classifier: Programming Language :: Python :: 3.12
Classifier: Programming Language :: Python :: 3.13
Classifier: Programming Language :: Python :: 3.8
Classifier: Topic :: Software Development :: Bug Tracking
Classifier: Topic :: Software Development :: Quality Assurance
Classifier: Topic :: Utilities
Requires-Dist: click (>=8.0.0,<9.0.0)
Requires-Dist: domd (>=2.1.4,<3.0.0)
Requires-Dist: pydantic (>=2.0.0,<3.0.0)
Requires-Dist: python-dotenv (>=1.0.0,<2.0.0)
Requires-Dist: requests (>=2.25.0,<3.0.0)
Requires-Dist: rich (>=13.0.0,<14.0.0)
Project-URL: Documentation, https://wronai.github.io/mdiss
Project-URL: Homepage, https://github.com/wronai/mdiss
Project-URL: Repository, https://github.com/wronai/mdiss.git
